ctcontour/__init__.py
ctcontour/__main__.py
ctcontour/config.py
ctcontour/contour_proc.py
ctcontour/contours.py
ctcontour/decorator_funcs.py
ctcontour/io_tools.py
ctcontour/plot_tools.py
ctcontour/slice.py
ctcontour-1.2.dist-info/LICENSE.txt
ctcontour-1.2.dist-info/METADATA
ctcontour-1.2.dist-info/WHEEL
ctcontour-1.2.dist-info/entry_points.txt
ctcontour-1.2.dist-info/top_level.txt
ctcontour-1.2.dist-info/RECORD
